feffery_markdown_components/FefferyMarkdown.py
feffery_markdown_components/FefferySyntaxHighlighter.py
feffery_markdown_components/__init__.py
feffery_markdown_components/_imports_.py
feffery_markdown_components/feffery_markdown_components.min.js
feffery_markdown_components/feffery_markdown_components.min.js.LICENSE.txt
feffery_markdown_components/feffery_markdown_components.min.js.map
feffery_markdown_components/metadata.json
feffery_markdown_components/package-info.json
feffery_markdown_components-0.4.3.dist-info/licenses/LICENSE
feffery_markdown_components-0.4.3.dist-info/METADATA
feffery_markdown_components-0.4.3.dist-info/WHEEL
feffery_markdown_components-0.4.3.dist-info/top_level.txt
feffery_markdown_components-0.4.3.dist-info/RECORD
